LICENSE
MANIFEST.in
README.rst
setup.py
zeek.py
zeek.egg-info/PKG-INFO
zeek.egg-info/SOURCES.txt
zeek.egg-info/dependency_links.txt
zeek.egg-info/entry_points.txt
zeek.egg-info/requires.txt
zeek.egg-info/top_level.txt