Metadata-Version: 1.1
Name: zeek
Version: 0.1.5
Summary: ZooKeeper CLI for caged animals
Home-page: http://github.com/krockode/zeek
Author: Kristian Perkins
Author-email: krockode@gmail.com
License: Apache 2.0
Platform: UNKNOWN
Classifier: Environment :: Console
Classifier: Development Status :: 3 - Alpha
Classifier: License :: OSI Approved :: Apache Software License
